LICENSE
MANIFEST.in
README.md
requirements.txt
setup.py
openalexnet/__init__.py
openalexnet/__main__.py
openalexnet/api.py
openalexnet/network.py
openalexnet/standalone.py
openalexnet/utilities.py
openalexnet.egg-info/PKG-INFO
openalexnet.egg-info/SOURCES.txt
openalexnet.egg-info/dependency_links.txt
openalexnet.egg-info/entry_points.txt
openalexnet.egg-info/requires.txt
openalexnet.egg-info/top_level.txt