Metadata-Version: 2.1
Name: openalexnet
Version: 0.1.1
Summary: Python library to load get networks from the OpenAlex API
Home-page: https://github.com/filipinascimento/openalexnet
Author: Filipi N. Silva
Author-email: filipinascimento@gmail.com
Classifier: Programming Language :: Python :: 3
Classifier: License :: OSI Approved :: MIT License
Classifier: Operating System :: OS Independent
Requires-Python: >=3.7
License-File: LICENSE
